{
  "model": "config-model random 2-factor (2m stubs paired)",
  "notes": "e_p_d_vanilla = e*pbar*(d_mean+1) using vertex-sharing dependency; vanilla LLL needs <=1 (fails by orders). red_config_frac = fraction of bad configs having >=1 reducing 2-switch (switching/entropy-compression viability).",
  "results": [
    {
      "m": 10,
      "n_cfg": 600,
      "n_red": 400,
      "K": 600,
      "E_B": 35.63666666666666,
      "N_candidates": 3874,
      "pbar": 0.00919893305799346,
      "d_mean": 36.348236834720794,
      "d_max": 67,
      "e_p_d_vanilla": 0.9339035891287317,
      "red_config_frac": 0.985,
      "mean_red_frac": 0.3587166666666667,
      "max_red_seen": 36,
      "sec": 50.6
    },
    {
      "m": 14,
      "n_cfg": 500,
      "n_red": 300,
      "K": 500,
      "E_B": 63.38,
      "N_candidates": 8516,
      "pbar": 0.007442461249412871,
      "d_mean": 60.553928684127484,
      "d_max": 103,
      "e_p_d_vanilla": 1.2452795065741347,
      "red_config_frac": 1.0,
      "mean_red_frac": 0.3622866666666667,
      "max_red_seen": 48,
      "sec": 68.2
    },
    {
      "m": 18,
      "n_cfg": 400,
      "n_red": 250,
      "K": 400,
      "E_B": 96.02,
      "N_candidates": 13430,
      "pbar": 0.007149664929262844,
      "d_mean": 84.24848989793793,
      "d_max": 127,
      "e_p_d_vanilla": 1.656787714353032,
      "red_config_frac": 1.0,
      "mean_red_frac": 0.37494,
      "max_red_seen": 52,
      "sec": 79.8
    },
    {
      "m": 22,
      "n_cfg": 300,
      "n_red": 200,
      "K": 300,
      "E_B": 132.91333333333333,
      "N_candidates": 16864,
      "pbar": 0.007881483238456673,
      "d_mean": 107.0903847118423,
      "d_max": 179,
      "e_p_d_vanilla": 2.3157384186296586,
      "red_config_frac": 1.0,
      "mean_red_frac": 0.39421666666666666,
      "max_red_seen": 56,
      "sec": 75.7
    },
    {
      "m": 26,
      "n_cfg": 250,
      "n_red": 150,
      "K": 250,
      "E_B": 172.416,
      "N_candidates": 20368,
      "pbar": 0.008465043205027493,
      "d_mean": 127.25668151447661,
      "d_max": 215,
      "e_p_d_vanilla": 2.951234096953869,
      "red_config_frac": 1.0,
      "mean_red_frac": 0.4161066666666666,
      "max_red_seen": 56,
      "sec": 75.4
    },
    {
      "m": 30,
      "n_cfg": 200,
      "n_red": 120,
      "K": 200,
      "E_B": 210.71,
      "N_candidates": 22364,
      "pbar": 0.00942183866928993,
      "d_mean": 143.35508518817332,
      "d_max": 227,
      "e_p_d_vanilla": 3.6971088120706708,
      "red_config_frac": 1.0,
      "mean_red_frac": 0.42745833333333333,
      "max_red_seen": 56,
      "sec": 60.5
    }
  ]
}